minato/__init__.py
minato/__main__.py
minato/cache.py
minato/commands/__init__.py
minato/commands/cache.py
minato/commands/list.py
minato/commands/remove.py
minato/commands/subcommand.py
minato/commands/update.py
minato/common/__init__.py
minato/common/filelock.py
minato/common/progress.py
minato/common/selector.py
minato/common/table.py
minato/common/url.py
minato/config.py
minato/exceptions.py
minato/filesystems/__init__.py
minato/filesystems/filesystem.py
minato/filesystems/gcs.py
minato/filesystems/hf.py
minato/filesystems/http.py
minato/filesystems/osfs.py
minato/filesystems/s3.py
minato/minato.py
minato/py.typed
minato/util.py
minato-0.12.3.dist-info/LICENSE
minato-0.12.3.dist-info/METADATA
minato-0.12.3.dist-info/WHEEL
minato-0.12.3.dist-info/entry_points.txt
minato-0.12.3.dist-info/RECORD
