Metadata-Version: 2.1
Name: minato
Version: 0.12.3
Summary: A Unified File I/O Library for Python
Home-page: https://github.com/altescy/minato
License: MIT
Keywords: python,cache,s3,google-cloud-storage
Author: Yasuhiro Yamaguchi
Author-email: me@altescy.jp
Requires-Python: >=3.8,<4.0
Classifier: License :: OSI Approved :: MIT License
Classifier: Programming Language :: Python :: 3
Classifier: Programming Language :: Python :: 3.8
Classifier: Programming Language :: Python :: 3.9
Classifier: Programming Language :: Python :: 3.10
Classifier: Programming Language :: Python :: 3.11
Classifier: Programming Language :: Python :: 3.12
Classifier: Programming Language :: Python :: 3.13
Provides-Extra: all
Provides-Extra: gcs
Provides-Extra: huggingface
Provides-Extra: s3
Requires-Dist: boto3 (>=1.9.201,<2.0) ; extra == "s3" or extra == "all"
Requires-Dist: google-cloud-storage (>=2.4,<3.0) ; extra == "gcs" or extra == "all"
Requires-Dist: huggingface-hub (>=0.8.1,<0.17.0) ; extra == "huggingface" or extra == "all"
Project-URL: Issues, https://github.com/altescy/minato/issues
